README.rst
setup.cfg
setup.py
nolearn/__init__.py
nolearn/_compat.py
nolearn/cache.py
nolearn/caffe.py
nolearn/dbn.py
nolearn/decaf.py
nolearn/grid_search.py
nolearn/inischema.py
nolearn/metrics.py
nolearn/overfeat.py
nolearn/util.py
nolearn.egg-info/PKG-INFO
nolearn.egg-info/SOURCES.txt
nolearn.egg-info/dependency_links.txt
nolearn.egg-info/not-zip-safe
nolearn.egg-info/requires.txt
nolearn.egg-info/top_level.txt
nolearn/lasagne/__init__.py
nolearn/lasagne/base.py
nolearn/lasagne/handlers.py
nolearn/lasagne/util.py
nolearn/lasagne/visualize.py
nolearn/tests/__init__.py
nolearn/tests/conftest.py
nolearn/tests/test_cache.py
nolearn/tests/test_grid_search.py
nolearn/tests/test_inischema.py
nolearn/tests/test_metrics.py