Metadata-Version: 2.1
Name: nolearn
Version: 0.6.1
Summary: scikit-learn compatible neural network library
Home-page: https://github.com/dnouri/nolearn
Author: Daniel Nouri
Author-email: daniel.nouri@gmail.com
License: MIT
Platform: UNKNOWN
Classifier: Development Status :: 4 - Beta
Classifier: Programming Language :: Python :: 2.7
Classifier: Programming Language :: Python :: 3.4
Provides-Extra: all
Provides-Extra: docs
Provides-Extra: gdbn
Provides-Extra: testing
Provides-Extra: visualization
